k8ops/__init__.py
k8ops/cli.py
k8ops/cluster/__init__.py
k8ops/cluster/drain.py
k8ops/cluster/summary.py
k8ops/types/__init__.py
k8ops/utils/__init__.py
k8ops/utils/parser.py
k8ops/utils/table.py
k8ops-0.0.2.dist-info/licenses/LICENSE
k8ops-0.0.2.dist-info/METADATA
k8ops-0.0.2.dist-info/WHEEL
k8ops-0.0.2.dist-info/entry_points.txt
k8ops-0.0.2.dist-info/top_level.txt
k8ops-0.0.2.dist-info/RECORD
