Metadata-Version: 2.4
Name: k8ops
Version: 0.0.2
Summary: Kubernetes Operations Tools
Author-email: nomagicln <nomagicln@gmail.com>
License-Expression: MIT
Project-URL: Homepage, https://github.com/nomagicln/k8ops
Project-URL: Bug Tracker, https://github.com/nomagicln/k8ops/issues
Keywords: kubernetes,k8s,operations,tools
Classifier: Environment :: Console
Classifier: Intended Audience :: System Administrators
Classifier: Programming Language :: Python :: 3
Classifier: Programming Language :: Python :: 3.7
Classifier: Programming Language :: Python :: 3.8
Classifier: Programming Language :: Python :: 3.9
Classifier: Programming Language :: Python :: 3.10
Classifier: Programming Language :: Python :: 3.11
Classifier: Programming Language :: Python :: 3.12
Classifier: Programming Language :: Python :: 3.13
Classifier: Topic :: System :: Systems Administration
Requires-Python: >=3.7
License-File: LICENSE
Requires-Dist: click>=8.1.8
Requires-Dist: tabulate>=0.9.0
Dynamic: license-file
